safeIO/__init__.py
safeIO-1.1.1.dist-info/LICENSE
safeIO-1.1.1.dist-info/METADATA
safeIO-1.1.1.dist-info/WHEEL
safeIO-1.1.1.dist-info/top_level.txt
safeIO-1.1.1.dist-info/RECORD
