Metadata-Version: 2.1
Name: safeIO
Version: 1.1.1
Summary: Safely make I/O operations to files in Python even from multiple threads... and more!
Home-page: https://github.com/Animenosekai/safeIO
Author: Anime no Sekai
Author-email: niichannomail@gmail.com
License: MIT
Download-URL: https://github.com/Animenosekai/safeIO/archive/v1.0.tar.gz
Keywords: file,io,thread-safe,thread,management,file-management,animenosekai,threading
Platform: UNKNOWN
Classifier: Development Status :: 4 - Beta
Classifier: License :: OSI Approved :: MIT License
Classifier: Programming Language :: Python :: 3
Classifier: Programming Language :: Python :: 3.3
Classifier: Programming Language :: Python :: 3.4
Classifier: Programming Language :: Python :: 3.5
Classifier: Programming Language :: Python :: 3.6
Classifier: Programming Language :: Python :: 3.7
Classifier: Programming Language :: Python :: 3.8
Classifier: Programming Language :: Python :: 3.9
